{
  "formats": [
    {
      "id": "csv",
      "displayName": "CSV",
      "description": "Configuration for the CSV/TSV format reader/writer",
      "extensions": [".csv"],
      "mimeTypes": ["text/csv"],
      "hasReader": true,
      "hasWriter": true,
      "groups": [
        {
          "id": "format",
          "label": "CSV Format Settings",
          "fields": ["separator", "textQualifier", "hasHeader", "columnNamesRow", "valuesStartRow"]
        },
        {
          "id": "extraction",
          "label": "Extraction",
          "fields": ["translatableColumns", "keyColumns", "commentColumns", "trimValues"]
        },
        {
          "id": "inlineCodes",
          "label": "Inline Codes",
          "fields": ["useCodeFinder", "codeFinderRules"]
        }
      ],
      "properties": {
        "codeFinderRules": {
          "type": "array",
          "description": "Regex patterns that match inline codes within translatable text",
          "widget": "code-finder"
        },
        "columnNamesRow": {
          "type": "integer",
          "description": "1-based row number containing column names. 0 means auto-detect.",
          "default": 0
        },
        "commentColumns": {
          "type": "array",
          "description": "Column indices (0-based) that contain comments or notes"
        },
        "hasHeader": {
          "type": "boolean",
          "description": "If true, the first row is treated as headers (non-translatable)",
          "default": true
        },
        "keyColumns": {
          "type": "array",
          "description": "Column indices (0-based) that provide the block ID (source ID / record ID)"
        },
        "separator": {
          "type": "string",
          "description": "Field delimiter character (comma for CSV, tab for TSV)",
          "default": ","
        },
        "textQualifier": {
          "type": "string",
          "description": "Character used to quote field values containing delimiters or newlines",
          "default": "\""
        },
        "translatableColumns": {
          "type": "array",
          "description": "Column indices (0-based) to extract as translatable content. If empty, all columns are translatable."
        },
        "trimValues": {
          "type": "boolean",
          "description": "If true, leading and trailing whitespace is removed from cell values",
          "default": false
        },
        "useCodeFinder": {
          "type": "boolean",
          "description": "Enable regex-based inline code detection within cell values",
          "default": false
        },
        "valuesStartRow": {
          "type": "integer",
          "description": "1-based row number where data values begin. 0 means auto-detect.",
          "default": 0
        }
      }
    },
    {
      "id": "doxygen",
      "displayName": "Doxygen Comments",
      "description": "Extracts translatable text from Doxygen/Javadoc comments in source code",
      "extensions": [".c", ".cpp", ".h", ".java", ".m", ".py"],
      "mimeTypes": ["text/x-doxygen-txt"],
      "hasReader": true,
      "hasWriter": true,
      "groups": [
        {
          "id": "parser",
          "label": "Parser Settings",
          "fields": ["preserveWhitespace"]
        },
        {
          "id": "inlineCodes",
          "label": "Inline Codes",
          "fields": ["useCodeFinder", "codeFinderRules"]
        }
      ],
      "properties": {
        "codeFinderRules": {
          "type": "array",
          "description": "Regex patterns that match inline codes within translatable text",
          "widget": "code-finder"
        },
        "preserveWhitespace": {
          "type": "boolean",
          "description": "Preserve original whitespace in extracted comment text instead of normalizing it",
          "default": false
        },
        "useCodeFinder": {
          "type": "boolean",
          "description": "Enable regex-based detection of inline codes within translatable text",
          "default": false
        }
      }
    },
    {
      "id": "dtd",
      "displayName": "DTD",
      "description": "",
      "extensions": [".dtd"],
      "mimeTypes": ["application/xml-dtd"],
      "hasReader": true,
      "hasWriter": true
    },
    {
      "id": "epub",
      "displayName": "EPUB E-Book",
      "description": "",
      "extensions": [".epub"],
      "mimeTypes": ["application/epub+zip"],
      "hasReader": true,
      "hasWriter": true
    },
    {
      "id": "exec",
      "displayName": "Exec (subprocess extractor)",
      "description": "",
      "extensions": null,
      "mimeTypes": null,
      "hasReader": true,
      "hasWriter": false
    },
    {
      "id": "fixedwidth",
      "displayName": "Fixed-Width",
      "description": "",
      "extensions": [".dat", ".fixed"],
      "mimeTypes": null,
      "hasReader": true,
      "hasWriter": true
    },
    {
      "id": "html",
      "displayName": "HTML",
      "description": "Configuration for the native HTML format reader/writer",
      "extensions": [".html", ".htm", ".xhtml"],
      "mimeTypes": ["text/html", "application/xhtml+xml"],
      "hasReader": true,
      "hasWriter": true,
      "groups": [
        {
          "id": "parser",
          "label": "Parser Settings",
          "fields": ["preserveWhitespace"]
        },
        {
          "id": "extraction",
          "label": "Extraction Rules",
          "fields": ["elements", "attributes"]
        },
        {
          "id": "inlineCodes",
          "label": "Inline Codes",
          "fields": ["useCodeFinder", "codeFinderRules"]
        }
      ],
      "properties": {
        "attributes": {
          "type": "object",
          "description": "Global attribute extraction rules -- maps attribute names to their rule configuration (ruleTypes, allElementsExcept, onlyTheseElements, conditions)"
        },
        "codeFinderRules": {
          "type": "array",
          "description": "Regex patterns that match inline codes within translatable text",
          "widget": "code-finder"
        },
        "elements": {
          "type": "object",
          "description": "Element extraction rules -- maps element names to their rule configuration (ruleTypes, conditions, idAttributes, translatableAttributes)"
        },
        "preserveWhitespace": {
          "type": "boolean",
          "description": "Preserve original whitespace in extracted text instead of collapsing it",
          "default": false
        },
        "useCodeFinder": {
          "type": "boolean",
          "description": "Enable regex-based detection of inline codes (placeholders, variables, tags) within translatable text",
          "default": false
        }
      }
    },
    {
      "id": "icml",
      "displayName": "ICML (Adobe InCopy)",
      "description": "",
      "extensions": [".icml", ".wcml"],
      "mimeTypes": ["application/x-icml+xml"],
      "hasReader": true,
      "hasWriter": true
    },
    {
      "id": "idml",
      "displayName": "Adobe InDesign Markup Language",
      "description": "",
      "extensions": [".idml"],
      "mimeTypes": ["application/vnd.adobe.indesign-idml-package"],
      "hasReader": true,
      "hasWriter": true
    },
    {
      "id": "json",
      "displayName": "JSON",
      "description": "Configuration for the native JSON format reader/writer",
      "extensions": [".json"],
      "mimeTypes": ["application/json"],
      "hasReader": true,
      "hasWriter": true,
      "groups": [
        {
          "id": "extraction",
          "label": "Extraction",
          "fields": ["extractAllPairs", "exceptions", "extractIsolatedStrings", "extractionRules"]
        },
        {
          "id": "naming",
          "label": "Block Naming",
          "fields": [
            "useKeyAsName",
            "useFullKeyPath",
            "useLeadingSlashOnKeyPath",
            "idRules",
            "useIdStack"
          ]
        },
        {
          "id": "subfilters",
          "label": "Subfilters",
          "fields": ["subfilters", "subfilter", "subfilterRules"]
        },
        {
          "id": "metadata",
          "label": "Metadata",
          "fields": ["noteRules", "genericMetaRules", "maxwidthRules", "maxwidthSizeUnit"]
        },
        {
          "id": "output",
          "label": "Output",
          "fields": ["escapeForwardSlashes"]
        },
        {
          "id": "inlineCodes",
          "label": "Inline Codes",
          "fields": ["useCodeFinder", "codeFinderRules"]
        }
      ],
      "properties": {
        "codeFinderRules": {
          "type": "array",
          "description": "Regex patterns that match inline codes within translatable text.",
          "widget": "code-finder"
        },
        "escapeForwardSlashes": {
          "type": "boolean",
          "description": "Escape forward slashes in output JSON (\\/).",
          "default": true
        },
        "exceptions": {
          "type": "string",
          "description": "Regex pattern for key names. When extractAllPairs is true, matching keys are excluded. When false, matching keys are included.",
          "widget": "regex"
        },
        "extractAllPairs": {
          "type": "boolean",
          "description": "Extract all key-value pairs for translation. When false, use extractionRules to specify which paths to extract.",
          "default": true
        },
        "extractIsolatedStrings": {
          "type": "boolean",
          "description": "Extract string values in arrays (without keys) as translatable blocks.",
          "default": false
        },
        "extractionRules": {
          "type": "string",
          "description": "Regex pattern for JSON paths to extract. Overrides extractAllPairs when specified.",
          "widget": "regex"
        },
        "genericMetaRules": {
          "type": "string",
          "description": "Regex for keys whose values become generic metadata.",
          "widget": "regex"
        },
        "idRules": {
          "type": "string",
          "description": "Regex for keys whose values become Block IDs (overrides useKeyAsName).",
          "widget": "regex"
        },
        "maxwidthRules": {
          "type": "string",
          "description": "Regex for keys whose values set max width constraints.",
          "widget": "regex"
        },
        "maxwidthSizeUnit": {
          "type": "string",
          "description": "Size unit for maxwidth.",
          "default": "pixel"
        },
        "noteRules": {
          "type": "string",
          "description": "Regex for keys whose values become translator notes.",
          "widget": "regex"
        },
        "subfilter": {
          "type": "string",
          "description": "Global subfilter format name (e.g., 'html') applied to all or matching extracted strings."
        },
        "subfilterRules": {
          "type": "string",
          "description": "Regex matching keys for which values should be processed with the sub-filter.",
          "widget": "regex"
        },
        "subfilters": {
          "type": "array",
          "description": "Array of {pattern, format} mappings for embedded content in specific keys."
        },
        "useCodeFinder": {
          "type": "boolean",
          "description": "Enable pattern-based detection of inline codes (placeholders, tags, etc.).",
          "default": false
        },
        "useFullKeyPath": {
          "type": "boolean",
          "description": "Use full path (/key1/key2) instead of immediate key as name.",
          "default": false
        },
        "useIdStack": {
          "type": "boolean",
          "description": "Build TextUnit IDs from nested key stack.",
          "default": false
        },
        "useKeyAsName": {
          "type": "boolean",
          "description": "Use JSON key as the Block (TextUnit) name for reference.",
          "default": true
        },
        "useLeadingSlashOnKeyPath": {
          "type": "boolean",
          "description": "Include leading slash in key path names.",
          "default": true
        }
      },
      "presets": [
        {
          "id": "i18next",
          "name": "i18next",
          "description": "",
          "parameters": {
            "subfilter": "html",
            "subfilterRules": "_html$",
            "useFullKeyPath": true
          }
        },
        {
          "id": "Chrome Extension",
          "name": "Chrome Extension",
          "description": "",
          "parameters": {
            "exceptions": "^message$",
            "extractAllPairs": false,
            "noteRules": "^description$"
          }
        }
      ]
    },
    {
      "id": "jsx",
      "displayName": "Kapi Localization Format (KLF)",
      "description": "",
      "extensions": [".klf"],
      "mimeTypes": ["application/vnd.neokapi.klf+json"],
      "hasReader": true,
      "hasWriter": true
    },
    {
      "id": "markdown",
      "displayName": "Markdown",
      "description": "Configuration for the Markdown format reader/writer",
      "extensions": [".md", ".markdown"],
      "mimeTypes": ["text/markdown", "text/x-markdown"],
      "hasReader": true,
      "hasWriter": true,
      "groups": [
        {
          "id": "extraction",
          "label": "Content Extraction",
          "fields": [
            "translateCodeBlocks",
            "translateFrontMatter",
            "translateImageAlt",
            "translateURLs",
            "translateBlockQuotes",
            "translateHTMLBlocks"
          ]
        },
        {
          "id": "output",
          "label": "Output",
          "fields": ["unescapeBackslashCharacters"]
        },
        {
          "id": "subfilters",
          "label": "Subfilters",
          "fields": ["subfilter"]
        },
        {
          "id": "inlineCodes",
          "label": "Inline Codes",
          "fields": ["useCodeFinder", "codeFinderRules"]
        }
      ],
      "properties": {
        "codeFinderRules": {
          "type": "array",
          "description": "Regex patterns that match inline codes within translatable text",
          "widget": "code-finder"
        },
        "subfilter": {
          "type": "string",
          "description": "Subfilter format to apply to HTML content within Markdown (e.g., 'html')"
        },
        "translateBlockQuotes": {
          "type": "boolean",
          "description": "If true, blockquote content is translatable.",
          "default": true
        },
        "translateCodeBlocks": {
          "type": "boolean",
          "description": "If true, fenced and indented code blocks are translatable. If false, emitted as non-translatable data.",
          "default": false
        },
        "translateFrontMatter": {
          "type": "boolean",
          "description": "If true, YAML front matter values are translatable. If false, emitted as non-translatable data.",
          "default": false
        },
        "translateHTMLBlocks": {
          "type": "boolean",
          "description": "If true, raw HTML blocks are translatable. If false, emitted as non-translatable data.",
          "default": false
        },
        "translateImageAlt": {
          "type": "boolean",
          "description": "If true, image alt text is included in translatable content.",
          "default": true
        },
        "translateURLs": {
          "type": "boolean",
          "description": "If true, link and image URLs are translatable.",
          "default": false
        },
        "unescapeBackslashCharacters": {
          "type": "boolean",
          "description": "Parse backslash-escaped punctuation in source documents",
          "default": false
        },
        "useCodeFinder": {
          "type": "boolean",
          "description": "Enable regex-based inline code detection within translatable text",
          "default": false
        }
      }
    },
    {
      "id": "messageformat",
      "displayName": "ICU MessageFormat",
      "description": "",
      "extensions": [".mf", ".messageformat"],
      "mimeTypes": ["text/x-messageformat"],
      "hasReader": true,
      "hasWriter": true
    },
    {
      "id": "mif",
      "displayName": "Adobe FrameMaker MIF",
      "description": "",
      "extensions": [".mif"],
      "mimeTypes": ["application/x-mif", "application/vnd.mif"],
      "hasReader": true,
      "hasWriter": true
    },
    {
      "id": "mo",
      "displayName": "MO (Gettext, binary)",
      "description": "Writer for compiled gettext MO catalogs. Consumes Blocks and emits a binary catalog keyed by (msgctxt, msgid). msgctxt is taken from Block.Properties[\"context\"] when present, else Block.Name, else Block.ID.",
      "extensions": [".mo"],
      "mimeTypes": ["application/x-gettext-translation"],
      "hasReader": true,
      "hasWriter": true
    },
    {
      "id": "mosestext",
      "displayName": "Moses Text",
      "description": "",
      "extensions": [],
      "mimeTypes": ["text/x-mosestext"],
      "hasReader": true,
      "hasWriter": true
    },
    {
      "id": "odf",
      "displayName": "Open Document Format",
      "description": "",
      "extensions": [".odt", ".ods", ".odp", ".odg", ".odf"],
      "mimeTypes": [
        "application/vnd.oasis.opendocument.text",
        "application/vnd.oasis.opendocument.spreadsheet",
        "application/vnd.oasis.opendocument.presentation"
      ],
      "hasReader": true,
      "hasWriter": true
    },
    {
      "id": "openxml",
      "displayName": "Office Open XML",
      "description": "Configuration for the DOCX/PPTX/XLSX format reader/writer",
      "extensions": [
        ".docx",
        ".docm",
        ".dotx",
        ".dotm",
        ".xlsx",
        ".xlsm",
        ".xltx",
        ".xltm",
        ".pptx",
        ".pptm",
        ".ppsx",
        ".potx"
      ],
      "mimeTypes": [
        "application/vnd.openxmlformats-officedocument.wordprocessingml.document",
        "application/vnd.openxmlformats-officedocument.presentationml.presentation",
        "application/vnd.openxmlformats-officedocument.spreadsheetml.sheet"
      ],
      "hasReader": true,
      "hasWriter": true,
      "groups": [
        {
          "id": "word",
          "label": "Word Options",
          "fields": [
            "translateDocProperties",
            "translateHiddenText",
            "translateHeadersFooters",
            "translateFootnotes",
            "translateComments",
            "translateHyperlinks",
            "automaticallyAcceptRevisions"
          ]
        },
        {
          "id": "excel",
          "label": "Excel Options",
          "fields": [
            "translateSheetNames",
            "translateSharedStrings",
            "excludedSheets",
            "excludedColumns"
          ]
        },
        {
          "id": "powerpoint",
          "label": "PowerPoint Options",
          "fields": [
            "translateSlideNotes",
            "translateSlideMasters",
            "translateHiddenSlides",
            "translateCharts",
            "translateDiagrams",
            "includedSlides"
          ]
        },
        {
          "id": "general",
          "label": "General",
          "fields": [
            "aggressiveCleanup",
            "tabAsCharacter",
            "ignoreSoftHyphenTag",
            "replaceNoBreakHyphenTag"
          ]
        },
        {
          "id": "styles",
          "label": "Style \u0026 Color Filtering",
          "collapsed": true,
          "fields": [
            "excludeColors",
            "excludeHighlightColors",
            "includeHighlightColors",
            "excludeStyles",
            "includeStyles"
          ]
        },
        {
          "id": "inlineCodes",
          "label": "Inline Codes",
          "collapsed": true,
          "fields": ["useCodeFinder", "codeFinderRules"]
        },
        {
          "id": "advanced",
          "label": "Advanced",
          "collapsed": true,
          "fields": [
            "complexFieldDefinitionsToExtract",
            "optimiseWordStyles",
            "fontMappings",
            "extractRunFontsInfo",
            "replaceLineSeparator",
            "lineSeparatorReplacement"
          ]
        }
      ],
      "properties": {
        "aggressiveCleanup": {
          "type": "boolean",
          "description": "Strip revision IDs, proofing errors, and other noise before merging runs.",
          "default": true
        },
        "automaticallyAcceptRevisions": {
          "type": "boolean",
          "description": "Automatically accept tracked changes before extraction.",
          "default": true
        },
        "codeFinderRules": {
          "type": "array",
          "description": "Regex patterns that match inline codes within translatable text.",
          "widget": "code-finder"
        },
        "complexFieldDefinitionsToExtract": {
          "type": "array",
          "description": "Field instruction prefixes to extract (e.g., \"HYPERLINK\", \"REF\")."
        },
        "excludeColors": {
          "type": "array",
          "description": "Font colors to exclude (hex RGB, e.g., \"FF0000\" for red)."
        },
        "excludeHighlightColors": {
          "type": "array",
          "description": "Highlight colors to exclude (e.g., \"yellow\", \"red\")."
        },
        "excludeStyles": {
          "type": "array",
          "description": "Paragraph/character style names to exclude."
        },
        "excludedColumns": {
          "type": "array",
          "description": "Column letters to exclude (e.g., \"A\", \"C\", \"AA\")."
        },
        "excludedSheets": {
          "type": "array",
          "description": "Sheet names to exclude from extraction."
        },
        "extractRunFontsInfo": {
          "type": "boolean",
          "description": "Emit font metadata as annotations on blocks.",
          "default": false
        },
        "fontMappings": {
          "type": "object",
          "description": "Font name to script group mapping (e.g., \"MS Gothic\": \"ja\")."
        },
        "ignoreSoftHyphenTag": {
          "type": "boolean",
          "description": "Ignore soft hyphen tags in the document.",
          "default": false
        },
        "includeHighlightColors": {
          "type": "array",
          "description": "If non-empty, only extract text with these highlight colors."
        },
        "includeStyles": {
          "type": "array",
          "description": "If non-empty, only extract text with these styles."
        },
        "includedSlides": {
          "type": "array",
          "description": "If non-empty, only extract these slide numbers (1-based)."
        },
        "lineSeparatorReplacement": {
          "type": "string",
          "description": "Replacement string for line separator characters.",
          "default": "\n"
        },
        "optimiseWordStyles": {
          "type": "boolean",
          "description": "Resolve style inheritance and strip redundant run properties.",
          "default": false
        },
        "replaceLineSeparator": {
          "type": "boolean",
          "description": "Replace Unicode line separator (U+2028) in output.",
          "default": false
        },
        "replaceNoBreakHyphenTag": {
          "type": "boolean",
          "description": "Replace no-break hyphen tags with the non-breaking hyphen character.",
          "default": false
        },
        "tabAsCharacter": {
          "type": "boolean",
          "description": "Treat tab elements as tab characters instead of placeholder spans.",
          "default": false
        },
        "translateCharts": {
          "type": "boolean",
          "description": "Extract strings from embedded charts.",
          "default": false
        },
        "translateComments": {
          "type": "boolean",
          "description": "Extract comment text from Word documents.",
          "default": false
        },
        "translateDiagrams": {
          "type": "boolean",
          "description": "Extract text from SmartArt diagrams.",
          "default": false
        },
        "translateDocProperties": {
          "type": "boolean",
          "description": "Extract title, subject, keywords from document properties.",
          "default": true
        },
        "translateFootnotes": {
          "type": "boolean",
          "description": "Extract footnotes and endnotes from Word documents.",
          "default": true
        },
        "translateHeadersFooters": {
          "type": "boolean",
          "description": "Extract text from headers and footers in Word documents.",
          "default": true
        },
        "translateHiddenSlides": {
          "type": "boolean",
          "description": "Extract content from hidden slides in PowerPoint.",
          "default": false
        },
        "translateHiddenText": {
          "type": "boolean",
          "description": "Extract text with the vanish (hidden) property in Word documents.",
          "default": false
        },
        "translateHyperlinks": {
          "type": "boolean",
          "description": "Extract hyperlink text for translation.",
          "default": true
        },
        "translateSharedStrings": {
          "type": "boolean",
          "description": "Extract shared strings from Excel workbooks.",
          "default": true
        },
        "translateSheetNames": {
          "type": "boolean",
          "description": "Extract sheet names in Excel workbooks.",
          "default": false
        },
        "translateSlideMasters": {
          "type": "boolean",
          "description": "Extract text from slide masters in PowerPoint.",
          "default": false
        },
        "translateSlideNotes": {
          "type": "boolean",
          "description": "Extract speaker notes in PowerPoint presentations.",
          "default": true
        },
        "useCodeFinder": {
          "type": "boolean",
          "description": "Enable pattern-based detection of inline codes (placeholders, tags, etc.).",
          "default": false
        }
      }
    },
    {
      "id": "paraplaintext",
      "displayName": "Paragraph Plain Text",
      "description": "",
      "extensions": null,
      "mimeTypes": null,
      "hasReader": true,
      "hasWriter": true
    },
    {
      "id": "pdf",
      "displayName": "PDF Text Extraction",
      "description": "",
      "extensions": [".pdf"],
      "mimeTypes": ["application/pdf"],
      "hasReader": true,
      "hasWriter": true
    },
    {
      "id": "phpcontent",
      "displayName": "PHP Content",
      "description": "Extracts translatable strings from PHP source files",
      "extensions": [".php", ".phpcnt"],
      "mimeTypes": ["application/x-php"],
      "hasReader": true,
      "hasWriter": true,
      "groups": [
        {
          "id": "extraction",
          "label": "Extraction settings",
          "fields": ["useDirectives", "extractOutsideDirectives"]
        }
      ],
      "properties": {
        "extractOutsideDirectives": {
          "type": "boolean",
          "description": "Extract translatable strings found outside directive-controlled regions.",
          "default": true
        },
        "useDirectives": {
          "type": "boolean",
          "description": "Honor //okapi: skip/text directives in PHP source to control extraction scope.",
          "default": true
        }
      }
    },
    {
      "id": "plaintext",
      "displayName": "Plain Text",
      "description": "Configuration for the plain text format reader/writer",
      "extensions": [".txt", ".text"],
      "mimeTypes": ["text/plain"],
      "hasReader": true,
      "hasWriter": true,
      "groups": [
        {
          "id": "segmentation",
          "label": "Segmentation",
          "fields": ["segmentByLine"]
        }
      ],
      "properties": {
        "segmentByLine": {
          "type": "boolean",
          "description": "If true, each line becomes a separate block. If false, paragraphs (separated by blank lines) are blocks.",
          "default": true
        }
      }
    },
    {
      "id": "po",
      "displayName": "PO (Gettext)",
      "description": "Configuration for the PO/POT format reader/writer",
      "extensions": [".po", ".pot"],
      "mimeTypes": ["text/x-gettext-translation"],
      "hasReader": true,
      "hasWriter": true,
      "groups": [
        {
          "id": "extraction",
          "label": "Extraction",
          "fields": ["preserveUntranslated"]
        },
        {
          "id": "mode",
          "label": "Processing Mode",
          "fields": ["bilingualMode"]
        },
        {
          "id": "output",
          "label": "Output",
          "fields": ["wrapContent", "allowEmptyOutputTarget"]
        },
        {
          "id": "inlineCodes",
          "label": "Inline Codes",
          "fields": ["useCodeFinder", "codeFinderRules"]
        }
      ],
      "properties": {
        "allowEmptyOutputTarget": {
          "type": "boolean",
          "description": "Allow empty target in output when no translation is available",
          "default": false
        },
        "bilingualMode": {
          "type": "boolean",
          "description": "In bilingual mode (default), msgid is the source text and msgstr is the target. In monolingual mode, msgid is treated as an ID.",
          "default": true
        },
        "codeFinderRules": {
          "type": "array",
          "description": "Regex patterns that match inline codes within translatable text",
          "widget": "code-finder"
        },
        "preserveUntranslated": {
          "type": "boolean",
          "description": "If true, entries with empty msgstr are emitted as blocks. If false, they are skipped.",
          "default": true
        },
        "useCodeFinder": {
          "type": "boolean",
          "description": "Enable regex-based inline code detection within PO message text",
          "default": false
        },
        "wrapContent": {
          "type": "boolean",
          "description": "Wrap long content lines in output at approximately 80 characters",
          "default": true
        }
      }
    },
    {
      "id": "properties",
      "displayName": "Java Properties",
      "description": "Configuration for the Java .properties format reader/writer",
      "extensions": [".properties"],
      "mimeTypes": ["text/x-java-properties"],
      "hasReader": true,
      "hasWriter": true,
      "groups": [
        {
          "id": "parsing",
          "label": "Parsing",
          "fields": ["separator"]
        },
        {
          "id": "extraction",
          "label": "Extraction",
          "fields": ["useKeyCondition", "extractOnlyMatchingKey", "keyCondition", "extraComments"]
        },
        {
          "id": "notes",
          "label": "Notes",
          "fields": ["commentsAreNotes"]
        },
        {
          "id": "output",
          "label": "Output",
          "fields": ["useJavaEscapes", "escapeExtendedChars"]
        },
        {
          "id": "inlineCodes",
          "label": "Inline Codes",
          "fields": ["useCodeFinder", "codeFinderRules"]
        }
      ],
      "properties": {
        "codeFinderRules": {
          "type": "array",
          "description": "Regex patterns that match inline codes within translatable text",
          "widget": "code-finder"
        },
        "commentsAreNotes": {
          "type": "boolean",
          "description": "Treat comments as translator notes attached to the following entry",
          "default": true
        },
        "escapeExtendedChars": {
          "type": "boolean",
          "description": "Escape extended Unicode characters (non-ASCII) in output using \\uXXXX notation",
          "default": true
        },
        "extraComments": {
          "type": "boolean",
          "description": "Recognize semicolon and double-slash comment styles in addition to standard # and ! markers",
          "default": false
        },
        "extractOnlyMatchingKey": {
          "type": "boolean",
          "description": "When enabled, extract only entries whose keys match the condition; otherwise exclude matching keys",
          "default": true
        },
        "keyCondition": {
          "type": "string",
          "description": "Regular expression pattern to test against property keys for extraction filtering",
          "default": ".*text.*",
          "widget": "regex"
        },
        "separator": {
          "type": "string",
          "description": "Key-value separator character (typically '=' or ':')",
          "default": "="
        },
        "useCodeFinder": {
          "type": "boolean",
          "description": "Enable regex-based inline code detection within property values",
          "default": false
        },
        "useJavaEscapes": {
          "type": "boolean",
          "description": "Keep Java property escape sequences (\\: \\= \\# \\!) in extracted text instead of resolving them",
          "default": false
        },
        "useKeyCondition": {
          "type": "boolean",
          "description": "Filter entries for extraction based on a regex condition applied to their keys",
          "default": false
        }
      }
    },
    {
      "id": "regex",
      "displayName": "Regex Extraction",
      "description": "",
      "extensions": [".strings", ".ini", ".info", ".rls"],
      "mimeTypes": ["text/x-regex"],
      "hasReader": true,
      "hasWriter": true
    },
    {
      "id": "rtf",
      "displayName": "Rich Text Format",
      "description": "",
      "extensions": [".rtf"],
      "mimeTypes": ["application/rtf", "text/rtf"],
      "hasReader": true,
      "hasWriter": true
    },
    {
      "id": "splicedlines",
      "displayName": "Spliced Lines",
      "description": "",
      "extensions": null,
      "mimeTypes": null,
      "hasReader": true,
      "hasWriter": true
    },
    {
      "id": "srt",
      "displayName": "SRT Subtitles",
      "description": "SubRip subtitle format — no configurable parameters",
      "extensions": [".srt"],
      "mimeTypes": ["application/x-subrip", "text/srt"],
      "hasReader": true,
      "hasWriter": true
    },
    {
      "id": "tex",
      "displayName": "TeX/LaTeX",
      "description": "",
      "extensions": [".tex", ".latex"],
      "mimeTypes": ["application/x-tex", "text/x-tex"],
      "hasReader": true,
      "hasWriter": true
    },
    {
      "id": "tmx",
      "displayName": "TMX",
      "description": "Configuration for the native TMX translation memory format reader/writer",
      "extensions": [".tmx"],
      "mimeTypes": ["application/x-tmx+xml"],
      "hasReader": true,
      "hasWriter": true,
      "groups": [
        {
          "id": "extraction",
          "label": "Extraction",
          "fields": ["processAllTargets", "exitOnInvalid"]
        },
        {
          "id": "output",
          "label": "Output",
          "fields": ["escapeGT"]
        },
        {
          "id": "inlineCodes",
          "label": "Inline Codes",
          "fields": ["useCodeFinder", "codeFinderRules"]
        }
      ],
      "properties": {
        "codeFinderRules": {
          "type": "array",
          "description": "Regex patterns that match inline codes within translatable text",
          "widget": "code-finder"
        },
        "escapeGT": {
          "type": "boolean",
          "description": "Escape \u003e as \u0026gt; in output XML",
          "default": false
        },
        "exitOnInvalid": {
          "type": "boolean",
          "description": "Stop processing when encountering invalid TUs. When false, invalid TUs are skipped.",
          "default": false
        },
        "processAllTargets": {
          "type": "boolean",
          "description": "Read all target language TUVs from each TU. When false, only the first target is read.",
          "default": true
        },
        "useCodeFinder": {
          "type": "boolean",
          "description": "Enable regex-based inline code detection in translatable text",
          "default": false
        }
      }
    },
    {
      "id": "transtable",
      "displayName": "Translation Table",
      "description": "",
      "extensions": [".tab", ".tsv"],
      "mimeTypes": ["text/tab-separated-values"],
      "hasReader": true,
      "hasWriter": true
    },
    {
      "id": "ts",
      "displayName": "Qt TS",
      "description": "",
      "extensions": [],
      "mimeTypes": ["application/x-ts", "application/x-linguist"],
      "hasReader": true,
      "hasWriter": true
    },
    {
      "id": "tsv",
      "displayName": "TSV",
      "description": "Configuration for the CSV/TSV format reader/writer",
      "extensions": [".tsv"],
      "mimeTypes": ["text/tab-separated-values"],
      "hasReader": true,
      "hasWriter": true,
      "groups": [
        {
          "id": "format",
          "label": "CSV Format Settings",
          "fields": ["separator", "textQualifier", "hasHeader", "columnNamesRow", "valuesStartRow"]
        },
        {
          "id": "extraction",
          "label": "Extraction",
          "fields": ["translatableColumns", "keyColumns", "commentColumns", "trimValues"]
        },
        {
          "id": "inlineCodes",
          "label": "Inline Codes",
          "fields": ["useCodeFinder", "codeFinderRules"]
        }
      ],
      "properties": {
        "codeFinderRules": {
          "type": "array",
          "description": "Regex patterns that match inline codes within translatable text",
          "widget": "code-finder"
        },
        "columnNamesRow": {
          "type": "integer",
          "description": "1-based row number containing column names. 0 means auto-detect.",
          "default": 0
        },
        "commentColumns": {
          "type": "array",
          "description": "Column indices (0-based) that contain comments or notes"
        },
        "hasHeader": {
          "type": "boolean",
          "description": "If true, the first row is treated as headers (non-translatable)",
          "default": true
        },
        "keyColumns": {
          "type": "array",
          "description": "Column indices (0-based) that provide the block ID (source ID / record ID)"
        },
        "separator": {
          "type": "string",
          "description": "Field delimiter character (comma for CSV, tab for TSV)",
          "default": ","
        },
        "textQualifier": {
          "type": "string",
          "description": "Character used to quote field values containing delimiters or newlines",
          "default": "\""
        },
        "translatableColumns": {
          "type": "array",
          "description": "Column indices (0-based) to extract as translatable content. If empty, all columns are translatable."
        },
        "trimValues": {
          "type": "boolean",
          "description": "If true, leading and trailing whitespace is removed from cell values",
          "default": false
        },
        "useCodeFinder": {
          "type": "boolean",
          "description": "Enable regex-based inline code detection within cell values",
          "default": false
        },
        "valuesStartRow": {
          "type": "integer",
          "description": "1-based row number where data values begin. 0 means auto-detect.",
          "default": 0
        }
      }
    },
    {
      "id": "ttml",
      "displayName": "TTML Subtitles",
      "description": "Timed Text Markup Language (W3C standard) subtitle format",
      "extensions": [".ttml", ".dfxp"],
      "mimeTypes": ["application/ttml+xml"],
      "hasReader": true,
      "hasWriter": true,
      "groups": [
        {
          "id": "extraction",
          "label": "Extraction",
          "fields": ["mergeAdjacentCaptions", "escapeBR"]
        },
        {
          "id": "output",
          "label": "Output settings",
          "fields": ["maxCharsPerLine", "maxLinesPerCaption", "cjkCharsPerLine", "splitWords"]
        }
      ],
      "properties": {
        "cjkCharsPerLine": {
          "type": "integer",
          "description": "Maximum number of characters per line for CJK languages. Set to 0 to disable.",
          "default": 0
        },
        "escapeBR": {
          "type": "boolean",
          "description": "When true, \u003cbr/\u003e elements are removed and text is joined with spaces; when false, \u003cbr/\u003e is preserved as literal text.",
          "default": true
        },
        "maxCharsPerLine": {
          "type": "integer",
          "description": "Maximum number of characters per line in output. Set to 0 to disable.",
          "default": 0
        },
        "maxLinesPerCaption": {
          "type": "integer",
          "description": "Maximum number of lines per caption in output. Set to 0 to disable.",
          "default": 0
        },
        "mergeAdjacentCaptions": {
          "type": "boolean",
          "description": "Merge adjacent \u003cp\u003e elements ending with trailing punctuation into one block.",
          "default": false
        },
        "splitWords": {
          "type": "boolean",
          "description": "Split words so that they don't go over the character limit per line.",
          "default": false
        }
      }
    },
    {
      "id": "ttx",
      "displayName": "Trados TagEditor TTX",
      "description": "",
      "extensions": [".ttx"],
      "mimeTypes": ["application/x-ttx+xml"],
      "hasReader": true,
      "hasWriter": true
    },
    {
      "id": "txml",
      "displayName": "Trados XML",
      "description": "",
      "extensions": [".txml"],
      "mimeTypes": ["application/x-txml+xml"],
      "hasReader": true,
      "hasWriter": true
    },
    {
      "id": "versifiedtext",
      "displayName": "Versified Text",
      "description": "",
      "extensions": [".ver"],
      "mimeTypes": null,
      "hasReader": true,
      "hasWriter": true
    },
    {
      "id": "vignette",
      "displayName": "R Vignette",
      "description": "",
      "extensions": [".Rmd", ".Rnw"],
      "mimeTypes": ["text/x-r-markdown"],
      "hasReader": true,
      "hasWriter": true
    },
    {
      "id": "vtt",
      "displayName": "WebVTT",
      "description": "Web Video Text Tracks (WebVTT) subtitle format",
      "extensions": [".vtt"],
      "mimeTypes": ["text/vtt"],
      "hasReader": true,
      "hasWriter": true,
      "groups": [
        {
          "id": "output",
          "label": "Output settings",
          "fields": ["maxCharsPerLine", "maxLinesPerCaption", "cjkCharsPerLine", "splitWords"]
        }
      ],
      "properties": {
        "cjkCharsPerLine": {
          "type": "integer",
          "description": "Maximum number of characters per line for CJK languages. Set to 0 to disable.",
          "default": 0
        },
        "maxCharsPerLine": {
          "type": "integer",
          "description": "Maximum number of characters per line in output. Set to 0 to disable.",
          "default": 0
        },
        "maxLinesPerCaption": {
          "type": "integer",
          "description": "Maximum number of lines per caption in output. Set to 0 to disable.",
          "default": 0
        },
        "splitWords": {
          "type": "boolean",
          "description": "Split words so that they don't go over the character limit per line.",
          "default": false
        }
      }
    },
    {
      "id": "wiki",
      "displayName": "Wiki",
      "description": "Configuration for the Wiki (MediaWiki/DokuWiki) format reader/writer",
      "extensions": [".wiki", ".mediawiki"],
      "mimeTypes": ["text/x-wiki"],
      "hasReader": true,
      "hasWriter": true,
      "groups": [
        {
          "id": "syntax",
          "label": "Syntax",
          "fields": ["variant", "preserveWhitespace"]
        }
      ],
      "properties": {
        "preserveWhitespace": {
          "type": "boolean",
          "description": "Preserve original whitespace in wiki markup instead of normalizing it.",
          "default": false
        },
        "variant": {
          "type": "string",
          "description": "Wiki markup variant: mediawiki or dokuwiki. Default is dokuwiki to match the okf_wiki bridge contract.",
          "default": "dokuwiki"
        }
      }
    },
    {
      "id": "xliff",
      "displayName": "XLIFF 1.2",
      "description": "Configuration for the native XLIFF 1.2 bilingual exchange format reader/writer",
      "extensions": [".xlf", ".xliff"],
      "mimeTypes": ["application/xliff+xml", "application/x-xliff+xml"],
      "hasReader": true,
      "hasWriter": true,
      "groups": [
        {
          "id": "extraction",
          "label": "Extraction",
          "fields": [
            "preserveSpaceByDefault",
            "includeExtensions",
            "includeIts",
            "ignoreInputSegmentation",
            "fallbackToID",
            "forceUniqueIds"
          ]
        },
        {
          "id": "states",
          "label": "Translation State Handling",
          "fields": ["useTranslationTargetState", "targetStateValue", "editAltTrans", "addAltTrans"]
        },
        {
          "id": "output",
          "label": "Output",
          "fields": [
            "addTargetLanguage",
            "overrideTargetLanguage",
            "allowEmptyTargets",
            "alwaysAddTargets"
          ]
        },
        {
          "id": "inlineCodes",
          "label": "Inline Codes",
          "fields": ["useCodeFinder", "codeFinderRules"]
        }
      ],
      "properties": {
        "addAltTrans": {
          "type": "boolean",
          "description": "Allow addition of new alt-trans elements",
          "default": false
        },
        "addTargetLanguage": {
          "type": "boolean",
          "description": "Add the target-language attribute to file elements if not already present",
          "default": true
        },
        "allowEmptyTargets": {
          "type": "boolean",
          "description": "Allow target elements with empty content to be written",
          "default": false
        },
        "alwaysAddTargets": {
          "type": "boolean",
          "description": "Add target elements for monolingual XLIFF files that have no target in the source",
          "default": false
        },
        "codeFinderRules": {
          "type": "array",
          "description": "Regex patterns that match inline codes within translatable text",
          "widget": "code-finder"
        },
        "editAltTrans": {
          "type": "boolean",
          "description": "Allow editing of existing alt-trans elements",
          "default": false
        },
        "fallbackToID": {
          "type": "boolean",
          "description": "Use the trans-unit id attribute as the block name when no resname attribute is present",
          "default": false
        },
        "forceUniqueIds": {
          "type": "boolean",
          "description": "Rewrite trans-unit IDs to enforce uniqueness across the file",
          "default": false
        },
        "ignoreInputSegmentation": {
          "type": "boolean",
          "description": "Ignore seg-source/mrk segmentation from the input XLIFF and treat the full source as a single segment",
          "default": false
        },
        "includeExtensions": {
          "type": "boolean",
          "description": "Include non-standard namespace extension elements in extracted content",
          "default": true
        },
        "includeIts": {
          "type": "boolean",
          "description": "Include ITS (Internationalization Tag Set) markup in extracted content",
          "default": true
        },
        "overrideTargetLanguage": {
          "type": "boolean",
          "description": "Override the target-language attribute in the output document with the pipeline target locale",
          "default": false
        },
        "preserveSpaceByDefault": {
          "type": "boolean",
          "description": "Treat all content as xml:space=\"preserve\" unless explicitly overridden",
          "default": false
        },
        "targetStateValue": {
          "type": "string",
          "description": "State value to set on target elements when useTranslationTargetState is enabled",
          "default": "needs-translation"
        },
        "useCodeFinder": {
          "type": "boolean",
          "description": "Enable regex-based inline code detection in translatable text",
          "default": false
        },
        "useTranslationTargetState": {
          "type": "boolean",
          "description": "Update the state attribute on target elements when writing translated XLIFF",
          "default": true
        }
      }
    },
    {
      "id": "xliff2",
      "displayName": "XLIFF 2.x",
      "description": "Configuration for the native XLIFF 2.0/2.1/2.2 bilingual exchange format reader/writer",
      "extensions": [".xlf", ".xliff"],
      "mimeTypes": ["application/xliff+xml"],
      "hasReader": true,
      "hasWriter": true,
      "groups": [
        {
          "id": "output",
          "label": "Output",
          "fields": ["version", "writeOriginalData"]
        },
        {
          "id": "extraction",
          "label": "Extraction",
          "fields": ["forceUniqueIds", "ignoreTagTypeMatch"]
        },
        {
          "id": "states",
          "label": "Translation State Handling",
          "fields": ["discardInvalidTargets"]
        },
        {
          "id": "inlineCodes",
          "label": "Inline Codes",
          "fields": ["useCodeFinder", "codeFinderRules"]
        }
      ],
      "properties": {
        "codeFinderRules": {
          "type": "array",
          "description": "Regex patterns that match inline codes within translatable text",
          "widget": "code-finder"
        },
        "discardInvalidTargets": {
          "type": "boolean",
          "description": "Discard targets that fail validation rather than rejecting the entire file",
          "default": false
        },
        "forceUniqueIds": {
          "type": "boolean",
          "description": "Ensure inline tag IDs are unique within each unit",
          "default": false
        },
        "ignoreTagTypeMatch": {
          "type": "boolean",
          "description": "Ignore tag type mismatch between source and target segments",
          "default": false
        },
        "useCodeFinder": {
          "type": "boolean",
          "description": "Enable regex-based inline code detection in translatable text",
          "default": false
        },
        "version": {
          "type": "string",
          "description": "Target XLIFF 2.x version to emit. Empty means: preserve the input document version on roundtrip, otherwise default to 2.2.",
          "default": ""
        },
        "writeOriginalData": {
          "type": "boolean",
          "description": "Output includes original data when available",
          "default": true
        }
      }
    },
    {
      "id": "xml",
      "displayName": "XML",
      "description": "Configuration for the generic XML format reader/writer",
      "extensions": [".xml"],
      "mimeTypes": ["text/xml", "application/xml"],
      "hasReader": true,
      "hasWriter": true,
      "groups": [
        {
          "id": "parser",
          "label": "Parser Settings",
          "fields": ["preserveWhitespace"]
        },
        {
          "id": "extraction",
          "label": "Extraction Rules",
          "fields": [
            "translatableElements",
            "translatableAttributes",
            "excludeByDefault",
            "inlineElements",
            "excludedElements",
            "preserveWhitespaceElements",
            "groupElements",
            "idAttributes"
          ]
        },
        {
          "id": "advanced",
          "label": "Advanced",
          "fields": ["elements", "attributes", "blockTypeMap"]
        },
        {
          "id": "subfilters",
          "label": "Subfilters",
          "fields": ["subfilters"]
        },
        {
          "id": "inlineCodes",
          "label": "Inline Codes",
          "fields": ["useCodeFinder", "codeFinderRules"]
        }
      ],
      "properties": {
        "attributes": {
          "type": "object",
          "description": "Advanced attribute-specific processing rules with element scope constraints"
        },
        "blockTypeMap": {
          "type": "object",
          "description": "Map of element names to block type strings for semantic type annotation"
        },
        "codeFinderRules": {
          "type": "array",
          "description": "Regex patterns that match inline codes within translatable text",
          "widget": "code-finder"
        },
        "elements": {
          "type": "object",
          "description": "Advanced element-specific processing rules with conditions, inline marking, and translatable attribute mappings"
        },
        "excludeByDefault": {
          "type": "boolean",
          "description": "Exclude all elements unless explicitly included by an element rule with INCLUDE",
          "default": false
        },
        "excludedElements": {
          "type": "array",
          "description": "Element names whose content is excluded from extraction"
        },
        "groupElements": {
          "type": "array",
          "description": "Element names that produce group/layer boundaries in the output"
        },
        "idAttributes": {
          "type": "array",
          "description": "Attribute names used to extract block IDs from elements"
        },
        "inlineElements": {
          "type": "array",
          "description": "Element names treated as inline (spans within text) rather than block-level"
        },
        "preserveWhitespace": {
          "type": "boolean",
          "description": "Preserve original whitespace in text content instead of collapsing it",
          "default": false
        },
        "preserveWhitespaceElements": {
          "type": "array",
          "description": "Element names that preserve whitespace regardless of the global setting"
        },
        "subfilters": {
          "type": "array",
          "description": "Array of {pattern, format} mappings for embedded content. Patterns use dot-separated element paths with glob support."
        },
        "translatableAttributes": {
          "type": "array",
          "description": "Attribute names that are translatable across all elements"
        },
        "translatableElements": {
          "type": "array",
          "description": "Element names whose text content is translatable. If empty, all text content is translatable."
        },
        "useCodeFinder": {
          "type": "boolean",
          "description": "Enable regex-based detection of inline codes within translatable text",
          "default": false
        }
      }
    },
    {
      "id": "yaml",
      "displayName": "YAML",
      "description": "Configuration for the native YAML format reader/writer",
      "extensions": [".yaml", ".yml"],
      "mimeTypes": ["application/yaml", "text/yaml", "application/x-yaml"],
      "hasReader": true,
      "hasWriter": true,
      "groups": [
        {
          "id": "extraction",
          "label": "Extraction",
          "fields": ["extractNonStrings", "keyPathPatterns"]
        },
        {
          "id": "subfilters",
          "label": "Subfilters",
          "fields": ["subfilter"]
        },
        {
          "id": "inlineCodes",
          "label": "Inline Codes",
          "fields": ["useCodeFinder", "codeFinderRules"]
        }
      ],
      "properties": {
        "codeFinderRules": {
          "type": "array",
          "description": "Regex patterns that match inline codes within translatable text",
          "widget": "code-finder"
        },
        "extractNonStrings": {
          "type": "boolean",
          "description": "Extract non-string scalar values (booleans, numbers, nulls) as translatable blocks",
          "default": false
        },
        "keyPathPatterns": {
          "type": "array",
          "description": "When non-empty, only keys matching one of these glob patterns are extracted. Supports * (single key) and ** (any depth)."
        },
        "subfilter": {
          "type": "string",
          "description": "Sub-filter to apply to scalar values (e.g., 'html' to process HTML within YAML values)"
        },
        "useCodeFinder": {
          "type": "boolean",
          "description": "Enable regex-based inline code detection within string values",
          "default": false
        }
      }
    }
  ]
}
