{
  "88031319": "TermEnforceItem",
  "92689182": "ListFlowDefinitions",
  "223814221": "LookupTerms",
  "274883483": "PseudoTranslateItem",
  "329111662": "Logout",
  "371450674": "ListProjects",
  "378219921": "StartWatching",
  "426528074": "PluginDir",
  "616177915": "RemoveConnector",
  "661014944": "DetectFormat",
  "663291304": "GetVersion",
  "668361826": "Disconnect",
  "686613052": "LoadPlugins",
  "696825198": "GetTMCount",
  "704585525": "FetchContent",
  "776322992": "ListPlugins",
  "794357047": "ExportTranslatedItem",
  "832952266": "SaveProviderConfig",
  "999425817": "GetProject",
  "1058981368": "TryAutoConnect",
  "1103546806": "SetApplication",
  "1112384681": "LookupTermsForBlock",
  "1139403919": "CreateStoreVersion",
  "1179732963": "GetWordCount",
  "1213282658": "DeleteFlowDefinition",
  "1240071736": "ListStoreVersions",
  "1353546789": "ReviewBlock",
  "1456548112": "SaveFlowDefinition",
  "1469074117": "LookupTMForBlock",
  "1554488048": "ListConnectorTypes",
  "1565988937": "StartLogin",
  "1584343218": "GetCurrentWorkspace",
  "1629877469": "AddConcept",
  "1701277356": "TMTranslateItem",
  "1757479876": "ImportTermsCSV",
  "1885409090": "StoreProject",
  "1916918101": "GetFlowDefinition",
  "1917252895": "ListContentItems",
  "1970959020": "DeleteProviderConfig",
  "2067629197": "GetTMEntries",
  "2110941316": "AddTMEntry",
  "2197315403": "ExportTermsJSON",
  "2234199739": "RenderDocumentPreview",
  "2350617666": "GetKnownLocales",
  "2403520224": "ListProjectFiles",
  "2510784253": "SelectWorkspace",
  "2559376511": "RemoveItem",
  "2593375276": "InitContentStore",
  "2593803262": "ImportTermsJSON",
  "2634747220": "HandleDeepLink",
  "2672799444": "PublishContent",
  "2777579616": "ConnectToServer",
  "2803823489": "GetConnectorStatus",
  "2826518989": "GetTermCount",
  "2901617344": "ListFormats",
  "2958338237": "StopWatching",
  "3045289771": "TestProviderConfig",
  "3159397869": "GetServerWorkspaces",
  "3166545228": "RenderBlockHTML",
  "3204097911": "GetPendingChangesCount",
  "3244055841": "WaitForLogin",
  "3257686637": "HandleAuthURL",
  "3303885562": "ListWorkspaces",
  "3374190367": "UpdateConcept",
  "3401740472": "UpdatePresence",
  "3416146777": "GetConnectionState",
  "3424415079": "GetTerms",
  "3445961939": "OpenFileInOS",
  "3484082396": "DeleteTMEntry",
  "3557611909": "DeleteConcept",
  "3605832733": "AddItems",
  "3615231647": "GetDefaultServerURL",
  "3730504007": "CancelLogin",
  "3731738086": "UpdateTMEntry",
  "3735242532": "ListProviderConfigs",
  "3766337077": "GetItemBlocks",
  "3768121167": "UpdateBlockTarget",
  "3843799473": "CloseProject",
  "3903261825": "UpdateBlockTargetRuns",
  "3952806715": "ListTools",
  "3954342840": "ListConnectors",
  "4069855585": "CreateProject",
  "4176435679": "ConfigureConnector",
  "4205376439": "GetLocaleDisplayName",
  "4233071499": "ListStoreProjects"
}
